README
setup.py
oerpenv/__init__.py
oerpenv/addon.py
oerpenv/defaults.py
oerpenv/environment.py
oerpenv/installable.py
oerpenv/repository.py
oerpenv/tools.py
oerpenv.egg-info/PKG-INFO
oerpenv.egg-info/SOURCES.txt
oerpenv.egg-info/dependency_links.txt
oerpenv.egg-info/requires.txt
oerpenv.egg-info/top_level.txt
scripts/oerpenv