Metadata-Version: 1.1
Name: oerpenv
Version: 1.8.1
Summary: OpenERP Environment Administrator
Home-page: http://business.moldeo.coop/
Author: Cristian S. Rocha
Author-email: cristian.rocha@moldeo.coop
License: UNKNOWN
Platform: UNKNOWN
Classifier: Development Status :: 5 - Production/Stable
Classifier: Environment :: Console
Classifier: Intended Audience :: Developers
Classifier: License :: OSI Approved :: GNU General Public License v3 or later (GPLv3+)
Classifier: Natural Language :: English
Classifier: Operating System :: Unix
Classifier: Programming Language :: Python :: 2.6
Classifier: Topic :: Software Development :: Build Tools
